custom_google_search/__init__.py
custom_google_search/api.py
custom_google_search-1.0.0.dist-info/LICENSE
custom_google_search-1.0.0.dist-info/METADATA
custom_google_search-1.0.0.dist-info/WHEEL
custom_google_search-1.0.0.dist-info/top_level.txt
custom_google_search-1.0.0.dist-info/RECORD
