Metadata-Version: 2.1
Name: custom-google-search
Version: 1.0.0
Summary: Performs custom google search programmatically
Home-page: https://github.com/joeyism/py-custom-google-search
Author: joeyism
License: UNKNOWN
Download-URL: https://github.com/joeyism/py-custom-google-search/archive/1.0.0.tar.gz
Keywords: custom,google,search,image,api,program
Platform: UNKNOWN
License-File: LICENSE
Requires-Dist: requests
